{
  "points": [
    {
      "id": 1,
      "name": "CRA Nantes",
      "latitude": 47.26733,
      "longitude": -1.502652,
      "description": "Lieu de construction du CRA de Nantes",
      "category": "CRA",
      "logo": "",
      "link": "",
      "address": "33 Rue de la Mainguais, 44470 Nantes, France"
    },
    {
      "id": 2,
      "name": "Egis",
      "latitude": 47.246771,
      "longitude": 1.507862,
      "description": "Entreprise d'ingénierie",
      "category": "Maîtrise d'ouvrage",
      "logo": "",
      "link": "",
      "address": "7 Rue de la Rainière, 44000 Nantes"
    },
    {
      "id": 3,
      "name": "Alma consulting",
      "latitude": 48.8627,
      "longitude": 2.4411,
      "description": "Ingénierie et conseil pour la restauration publique et privée, appui dans la construction et rénovation de bâtiments publics, sur la partie hôtellerie / restauration",
      "category": "Entreprise",
      "logo": "",
      "link": "",
      "address": "4 rue Dolorès Ibarruri et 66 rue Marceau, Montreuil (Seine-Saint-Denis)"
    }
  ]
}
